CHANGES.txt
LICENSE.txt
README.txt
buildout.cfg
setup.py
bootstrap/bootstrap.py
src/zope/__init__.py
src/zope.introspector.egg-info/PKG-INFO
src/zope.introspector.egg-info/SOURCES.txt
src/zope.introspector.egg-info/dependency_links.txt
src/zope.introspector.egg-info/entry_points.txt
src/zope.introspector.egg-info/namespace_packages.txt
src/zope.introspector.egg-info/not-zip-safe
src/zope.introspector.egg-info/requires.txt
src/zope.introspector.egg-info/top_level.txt
src/zope/introspector/README.txt
src/zope/introspector/__init__.py
src/zope/introspector/adapters.py
src/zope/introspector/adapters.txt
src/zope/introspector/code.py
src/zope/introspector/code.txt
src/zope/introspector/configure.zcml
src/zope/introspector/ftesting.zcml
src/zope/introspector/infos.py
src/zope/introspector/interfaces.py
src/zope/introspector/introspector.txt
src/zope/introspector/meta.py
src/zope/introspector/meta.zcml
src/zope/introspector/objectinfo.py
src/zope/introspector/objectinfo.txt
src/zope/introspector/registry.py
src/zope/introspector/registry.txt
src/zope/introspector/util.py
src/zope/introspector/util.txt
src/zope/introspector/viewinfo.py
src/zope/introspector/viewinfo.txt
src/zope/introspector/tests/__init__.py
src/zope/introspector/tests/registries.py
src/zope/introspector/tests/test_zopeintrospector.py