Metadata-Version: 1.0
Name: zope.introspector
Version: 0.1.1
Summary: Introspection helpers for Zope and Python objects.
Home-page: http://pypi.python.org/pypi/zope.introspector
Author: Zope Corporation and Contributors
Author-email: zope3-dev@zope.org
License: ZPL 2.1
Keywords: zope zope2 zope3 web introspection introspector
Platform: UNKNOWN
Classifier: Development Status :: 3 - Alpha
Classifier: Environment :: Web Environment
Classifier: Intended Audience :: Developers
Classifier: License :: OSI Approved :: Zope Public License
Classifier: Programming Language :: Python
Classifier: Natural Language :: English
Classifier: Operating System :: OS Independent
Classifier: Topic :: Internet :: WWW/HTTP
Classifier: Framework :: Zope3
